odoo/addons/l10n_ro_pos/README.rst
odoo/addons/l10n_ro_pos/__init__.py
odoo/addons/l10n_ro_pos/__manifest__.py
odoo/addons/l10n_ro_pos/i18n/l10n_ro_pos.pot
odoo/addons/l10n_ro_pos/i18n/ro.po
odoo/addons/l10n_ro_pos/models/__init__.py
odoo/addons/l10n_ro_pos/models/pos_order.py
odoo/addons/l10n_ro_pos/models/pos_session.py
odoo/addons/l10n_ro_pos/readme/CONTRIBUTORS.rst
odoo/addons/l10n_ro_pos/readme/DESCRIPTION.rst
odoo/addons/l10n_ro_pos/report/__init__.py
odoo/addons/l10n_ro_pos/report/pos_invoice.py
odoo/addons/l10n_ro_pos/report/pos_order.py
odoo/addons/l10n_ro_pos/static/description/icon.png
odoo/addons/l10n_ro_pos/static/description/icon.svg
odoo/addons/l10n_ro_pos/static/description/index.html
odoo/addons/l10n_ro_pos/static/src/css/pos.css
odoo/addons/l10n_ro_pos/static/src/js/PaymentScreenStatus.js
odoo/addons/l10n_ro_pos/static/src/xml/pos.xml
odoo/addons/l10n_ro_pos/tests/__init__.py
odoo/addons/l10n_ro_pos/tests/test_pos.py
odoo/addons/l10n_ro_pos/views/assets.xml
odoo/addons/l10n_ro_pos/views/report_saledetails.xml
odoo/addons/l10n_ro_pos/wizard/__init__.py
odoo/addons/l10n_ro_pos/wizard/pos_payment.py
odoo14_addon_l10n_ro_pos-14.0.2.3.0.dist-info/METADATA
odoo14_addon_l10n_ro_pos-14.0.2.3.0.dist-info/WHEEL
odoo14_addon_l10n_ro_pos-14.0.2.3.0.dist-info/top_level.txt
odoo14_addon_l10n_ro_pos-14.0.2.3.0.dist-info/RECORD
