Metadata-Version: 2.1
Name: odoo14-addon-l10n-ro-pos
Version: 14.0.2.3.0
Summary: Romania - Point of Sale
Home-page: https://github.com/OCA/l10n-romania
Author: Terrabit,Odoo Community Association (OCA)
Author-email: support@odoo-community.org
License: AGPL-3
Platform: UNKNOWN
Classifier: Programming Language :: Python
Classifier: Framework :: Odoo
Classifier: Framework :: Odoo :: 14.0
Classifier: License :: OSI Approved :: GNU Affero General Public License v3
Requires-Python: >=3.6
Requires-Dist: odoo14-addon-l10n-ro-config
Requires-Dist: odoo14-addon-l10n-ro-stock
Requires-Dist: odoo <14.1dev,>=14.0a
